flet_localization/__init__.py
flet_localization-0.1.0.dist-info/LICENSE
flet_localization-0.1.0.dist-info/METADATA
flet_localization-0.1.0.dist-info/WHEEL
flet_localization-0.1.0.dist-info/RECORD
