Metadata-Version: 2.1
Name: flet_localization
Version: 0.1.0
Summary: An addon for advanced localization.
Author: tct123
Author-email: 42028373+tct123@users.noreply.github.com
Requires-Python: >=3.10,<4.0
Classifier: Programming Language :: Python :: 3
Classifier: Programming Language :: Python :: 3.10
Classifier: Programming Language :: Python :: 3.11
Classifier: Programming Language :: Python :: 3.12
Classifier: Programming Language :: Python :: 3.13
